iotronic_lightningrod/Board.py
iotronic_lightningrod/__init__.py
iotronic_lightningrod/config.py
iotronic_lightningrod/lightningrod.py
iotronic_lightningrod/wampmessage.py
iotronic_lightningrod/common/__init__.py
iotronic_lightningrod/common/exception.py
iotronic_lightningrod/common/pam.py
iotronic_lightningrod/common/utils.py
iotronic_lightningrod/devices/Device.py
iotronic_lightningrod/devices/__init__.py
iotronic_lightningrod/devices/arancino.py
iotronic_lightningrod/devices/generic.py
iotronic_lightningrod/devices/raspberry.py
iotronic_lightningrod/devices/server.py
iotronic_lightningrod/devices/yun.py
iotronic_lightningrod/devices/gpio/Gpio.py
iotronic_lightningrod/devices/gpio/__init__.py
iotronic_lightningrod/devices/gpio/arancino.py
iotronic_lightningrod/devices/gpio/generic.py
iotronic_lightningrod/devices/gpio/raspberry.py
iotronic_lightningrod/devices/gpio/server.py
iotronic_lightningrod/devices/gpio/yun.py
iotronic_lightningrod/etc/iotronic/iotronic.conf
iotronic_lightningrod/etc/logrotate.d/lightning-rod.log
iotronic_lightningrod/etc/systemd/system/s4t-lightning-rod.service
iotronic_lightningrod/modules/Module.py
iotronic_lightningrod/modules/__init__.py
iotronic_lightningrod/modules/device_manager.py
iotronic_lightningrod/modules/network_manager.py
iotronic_lightningrod/modules/plugin_manager.py
iotronic_lightningrod/modules/rest_manager.py
iotronic_lightningrod/modules/service_manager.py
iotronic_lightningrod/modules/utils.py
iotronic_lightningrod/modules/webservice_manager.py
iotronic_lightningrod/modules/plugins/Plugin.py
iotronic_lightningrod/modules/plugins/PluginSerializer.py
iotronic_lightningrod/modules/plugins/__init__.py
iotronic_lightningrod/modules/plugins/pluginApis.py
iotronic_lightningrod/modules/plugins/plugins_examples/arduino_yun/demo.py
iotronic_lightningrod/modules/plugins/plugins_examples/arduino_yun/led.json
iotronic_lightningrod/modules/plugins/plugins_examples/arduino_yun/led.py
iotronic_lightningrod-0.5.0.dist-info/AUTHORS
iotronic_lightningrod-0.5.0.dist-info/LICENSE
iotronic_lightningrod-0.5.0.dist-info/METADATA
iotronic_lightningrod-0.5.0.dist-info/WHEEL
iotronic_lightningrod-0.5.0.dist-info/entry_points.txt
iotronic_lightningrod-0.5.0.dist-info/top_level.txt
iotronic_lightningrod-0.5.0.dist-info/RECORD
