Metadata-Version: 2.1
Name: iotronic-lightningrod
Version: 0.5.0
Summary: Implementation of the Lightning-rod, the Stack4Things board-side probe
Home-page: http://stack4things.unime.it/
Author: Nicola Peditto
Author-email: n.peditto@gmail.com
License: UNKNOWN
Platform: UNKNOWN
Classifier: Environment :: OpenStack
Classifier: Intended Audience :: Information Technology
Classifier: Intended Audience :: System Administrators
Classifier: License :: OSI Approved :: Apache Software License
Classifier: Operating System :: POSIX :: Linux
Classifier: Programming Language :: Python
Classifier: Programming Language :: Python :: 3
Classifier: Programming Language :: Python :: 3.6
Classifier: Programming Language :: Python :: 3.7
Classifier: Programming Language :: Python :: 3.8
Requires-Dist: Flask (!=0.11,>=1.0.2)
Requires-Dist: autobahn (>=18.10.1)
Requires-Dist: httplib2 (>=0.9.1)
Requires-Dist: oslo.config (>=5.1.0)
Requires-Dist: oslo.log (>=3.36.0)
Requires-Dist: pbr (!=2.1.0,>=2.0.0)
Requires-Dist: psutil (>=5.4.7)
Requires-Dist: pyOpenSSL (>=16.2.0)
Requires-Dist: six (>=1.10.0)
Requires-Dist: pyinotify (>=0.9.6) ; (sys_platform!='win32' and sys_platform!='darwin' and sys_platform!='sunos5')
